valve_gfx_ci/executor/client/__init__.py
valve_gfx_ci/executor/client/__main__.py
valve_gfx_ci/executor/client/client.py
valve_gfx_ci/executor/client/message.py
valve_gfx_ci.executor.client-0.0.9.dist-info/LICENSE
valve_gfx_ci.executor.client-0.0.9.dist-info/METADATA
valve_gfx_ci.executor.client-0.0.9.dist-info/WHEEL
valve_gfx_ci.executor.client-0.0.9.dist-info/entry_points.txt
valve_gfx_ci.executor.client-0.0.9.dist-info/top_level.txt
valve_gfx_ci.executor.client-0.0.9.dist-info/RECORD
